{
  "project_info": {
    "project_number": "803774630900",
    "project_id": "ahymobapp",
    "storage_bucket": "ahymobapp.appspot.com"
  },
  "client": [
    {
      "client_info": {
        "mobilesdk_app_id": "1:803774630900:android:643ed55cfc72cc0e0f47a1",
        "android_client_info": {
          "package_name": "com.angelica"
        }
      },
      "oauth_client": [
        {
          "client_id": "803774630900-p45dr1q3tj5nkr7nd13q52i0k1ai6hj4.apps.googleusercontent.com",
          "client_type": 1,
          "android_info": {
            "package_name": "com.angelica",
            "certificate_hash": "5e8f16062ea3cd2c4a0d547876baa6f38cabf625"
          }
        },
        {
          "client_id": "803774630900-8bao69qodd7ab57b2gno7ok97gjilhqo.apps.googleusercontent.com",
          "client_type": 3
        }
      ],
      "api_key": [
        {
          "current_key": "AIzaSyBkh0dlM5p9SlWjUwwuwU9Lo2fv7QcwWQ8"
        }
      ],
      "services": {
        "appinvite_service": {
          "other_platform_oauth_client": [
            {
              "client_id": "803774630900-8bao69qodd7ab57b2gno7ok97gjilhqo.apps.googleusercontent.com",
              "client_type": 3
            }
          ]
        }
      }
    }
  ],
  "configuration_version": "1"
}